__init__.py
pyaurn.py
pyaurn-0.1.21.dist-info/LICENSE
pyaurn-0.1.21.dist-info/METADATA
pyaurn-0.1.21.dist-info/WHEEL
pyaurn-0.1.21.dist-info/top_level.txt
pyaurn-0.1.21.dist-info/RECORD
