Metadata-Version: 2.1
Name: pyaurn
Version: 0.1.21
Summary: Package to import air quality data from UK and European sites. Mirrors the functionality of the R package 'openair'.
Author-email: Anthony Walker <walker.anthony91@gmail.com>, Robin Wilson <robin@rtwilson.com>
Project-URL: Homepage, https://github.com/robintw/PyAURN
Project-URL: Bug Tracker, https://github.com/robintw/PyAURN/issues
Classifier: Programming Language :: Python :: 3
Classifier: License :: OSI Approved :: MIT License
Classifier: Operating System :: OS Independent
Requires-Python: >=3.7
License-File: LICENSE
Requires-Dist: pyreadr
Requires-Dist: pandas
Requires-Dist: tqdm
Requires-Dist: windrose
